{
  "Stop Recording": "Oprește înregistrarea",
  "Record": "Înregistrează",
  "Stop": "Oprește",
  "Play": "Redă",
  "Save Recording": "Salvează înregistrarea",
  "Enter recording name": "Introduceți numele înregistrării",
  "Replay delay": "Întârziere reluare",
  "Minutes": "Minute",
  "Seconds": "Secunde",
  "Mantras": "Mantre",
  "Add your recording here...": "Adăugați înregistrarea aici...",
  "enterText": "Introduceți textul aici",
  "delayInSeconds": "Întârziere în secunde:",
  "speechRate": "Rata de vorbire:",
  "stopSpeaking": "Opriți vorbirea",
  "textToSpeech": "Text în vorbire",
  "home": "Acasă",
  "repeat": "Repetă",
  "mantra1": "Mintea mea este clară și concentrată.",
  "mantra2": "Sunt recunoscător pentru abundența din viața mea.",
  "mantra3": "Sunt puternic și capabil.",
  "mantra4": "Sunt pe deplin prezent în acest moment.",
  "mantra5": "Sunt în pace cu mine însumi și cu lumea."
}
